lazifetch/__init__.py
lazifetch/model/OpenAILLM.py
lazifetch/model/Result.py
lazifetch/model/SemanticSearcher.py
lazifetch/model/__init__.py
lazifetch/utils/__init__.py
lazifetch/utils/llm.py
lazifetch-0.0.8.dist-info/licenses/LICENSE
lazifetch-0.0.8.dist-info/METADATA
lazifetch-0.0.8.dist-info/WHEEL
lazifetch-0.0.8.dist-info/top_level.txt
lazifetch-0.0.8.dist-info/RECORD
