Metadata-Version: 2.4
Name: lazifetch
Version: 0.0.8
Summary: A Python package for searching and downloading academic literature based on topics.
License: MIT
Requires-Python: >=3.13
License-File: LICENSE
Requires-Dist: aiohttp>=3.13.1
Requires-Dist: numpy>=2.3.4
Requires-Dist: openai>=1.0.0
Requires-Dist: pillow>=12.0.0
Requires-Dist: pip>=25.3
Requires-Dist: python-dotenv>=1.2.1
Requires-Dist: requests>=2.32.5
Requires-Dist: tenacity>=9.1.2
Dynamic: license-file
